<?xml version="1.0" encoding="UTF-8"?>
<beans xmlns="http://www.springframework.org/schema/beans"
	xmlns:xsi="http://www.w3.org/2001/XMLSchema-instance"
	xsi:schemaLocation="http://www.springframework.org/schema/beans
        http://www.springframework.org/schema/beans/spring-beans.xsd">

	<import resource="classpath:/ctx/spring/dao/wm-dao-spring.xml"/>

	<import resource="classpath:/ctx/spring/datasource/wm-datasource-spring.xml"/>

	<import resource="classpath:/ctx/spring/jpa/wm-jpa-spring.xml"/>
	
	<import resource="classpath:/ctx/spring/placeholder/wm-placeholder-spring.xml"/>
	
	<import resource="classpath:/ctx/spring/service/wm-service-spring.xml"/>
	
	<import resource="classpath:/ctx/spring/ws/wm-wservices-spring.xml"/>
	
	<import resource="classpath:/ctx/spring/security/wm-security-spring.xml"/>
	
	<import resource="classpath:/ctx/spring/transaction/wm-transaction-spring.xml"/>

</beans>